cyberjake/__init__.py
cyberjake/_utils.py
cyberjake/check_update.py
cyberjake/database.py
cyberjake/discord_common.py
cyberjake/file_utils.py
cyberjake/make_logger.py
cyberjake/text_utils.py
cyberjake-0.2.1.dist-info/LICENSE
cyberjake-0.2.1.dist-info/METADATA
cyberjake-0.2.1.dist-info/WHEEL
cyberjake-0.2.1.dist-info/RECORD
