Metadata-Version: 2.1
Name: cyberjake
Version: 0.2.1
Summary: Common Python utilities for Cyb3r-Jak3 projects
License: MPL-2.0
Keywords: common,cyb3rjak3
Author: Cyb3r-Jak3
Requires-Python: >=3.10
Classifier: License :: OSI Approved
Classifier: Programming Language :: Python :: 3
Classifier: Programming Language :: Python :: 3.10
Classifier: Programming Language :: Python :: 3.11
Classifier: Programming Language :: Python :: 3.12
